material_zui/.pypirc
material_zui/bard/__init__.py
material_zui/bard/google_bard.py
material_zui/bard/index.py
material_zui/bing_ai/__init__.py
material_zui/bing_ai/bing_ai.py
material_zui/bing_ai/index.py
material_zui/bing_ai/result.py
material_zui/bing_ai/type.py
material_zui/compress/__init__.py
material_zui/compress/index.py
material_zui/compress/text.py
material_zui/crawl/__init__.py
material_zui/crawl/image.py
material_zui/crawl/index.py
material_zui/crontab/__init__.py
material_zui/crontab/index.py
material_zui/date_time/__init__.py
material_zui/date_time/date_time.py
material_zui/date_time/index.py
material_zui/date_time/time.py
material_zui/dict/__init__.py
material_zui/dict/common.py
material_zui/dict/index.py
material_zui/env/__init__.py
material_zui/env/env.py
material_zui/env/index.py
material_zui/fake/__init__.py
material_zui/fake/index.py
material_zui/fake/number.py
material_zui/file/__init__.py
material_zui/file/check.py
material_zui/file/common.py
material_zui/file/download.py
material_zui/file/excel.py
material_zui/file/index.py
material_zui/file/read.py
material_zui/file/remove.py
material_zui/file/type.py
material_zui/file/write.py
material_zui/generate/__init__.py
material_zui/generate/common.py
material_zui/generate/index.py
material_zui/gpt/__init__.py
material_zui/gpt/gpt_vietnam.py
material_zui/gpt/index.py
material_zui/image/__init__.py
material_zui/image/colorization.py
material_zui/image/combine.py
material_zui/image/common.py
material_zui/image/convert.py
material_zui/image/data.py
material_zui/image/index.py
material_zui/image/model/colorization_deploy_v2.prototxt
material_zui/image/model/pts_in_hull.npy
material_zui/image/remove_background.py
material_zui/image/to_svg.py
material_zui/image/transparent_background.py
material_zui/image/type.py
material_zui/image/upscale.py
material_zui/list/__init__.py
material_zui/list/common.py
material_zui/list/index.py
material_zui/list/test.py
material_zui/log/__init__.py
material_zui/log/common.py
material_zui-0.1.7.dist-info/METADATA
material_zui-0.1.7.dist-info/WHEEL
material_zui-0.1.7.dist-info/RECORD
