Metadata-Version: 2.1
Name: material_zui
Version: 0.1.7
Summary: Material Zui
Keywords: material,zui,material zui,zui material
Author: chauhmnguyen
Author-email: chauhoangminhnguyen@gmail.com
Requires-Python: >=3.10,<3.11
Classifier: Programming Language :: Python :: 3
Classifier: Programming Language :: Python :: 3.10
Requires-Dist: babel (>=2.15.0,<3.0.0)
Requires-Dist: bardapi (>=0.1.2,<0.2.0)
Requires-Dist: beautifulsoup4 (>=4.12.2,<5.0.0)
Requires-Dist: ccxt (>=4.4.40,<5.0.0)
Requires-Dist: edgegpt (>=0.11.6,<0.12.0)
Requires-Dist: flask (>=2.3.2,<3.0.0)
Requires-Dist: free-proxy (>=1.1.1,<2.0.0)
Requires-Dist: googletrans-py (>=4.0.0,<5.0.0)
Requires-Dist: huggingface-hub (>=0.15.1,<0.16.0)
Requires-Dist: langchain (>=0.0.216,<0.0.217)
Requires-Dist: matplotlib (>=3.7.1,<4.0.0)
Requires-Dist: multipledispatch (>=0.6.0,<0.7.0)
Requires-Dist: newspaper3k (>=0.2.8,<0.3.0)
Requires-Dist: numpy (>=1.24.3,<2.0.0)
Requires-Dist: opencv-python (>=4.7.0.72,<5.0.0.0)
Requires-Dist: pandas (>=2.0.1,<3.0.0)
Requires-Dist: pillow (>=9.5.0,<10.0.0)
Requires-Dist: pytelegrambotapi (>=4.11.0,<5.0.0)
Requires-Dist: python-crontab (>=2.7.1,<3.0.0)
Requires-Dist: python-dotenv (>=1.0.0,<2.0.0)
Requires-Dist: pythonlangutil (>=0.1,<0.2)
Requires-Dist: pyttsx3 (>=2.90,<3.0)
Requires-Dist: pytube (>=15.0.0,<16.0.0)
Requires-Dist: rembg (>=2.0.36,<3.0.0)
Requires-Dist: replicate (>=0.8.1,<0.9.0)
Requires-Dist: requests (>=2.31.0,<3.0.0)
Requires-Dist: selenium (>=4.9.1,<5.0.0)
Requires-Dist: selenium-browser (>=0.0.15,<0.0.16)
Requires-Dist: setuptools (>=67.8.0,<68.0.0)
Requires-Dist: socks (>=0,<1)
Requires-Dist: streamlit (>=1.24.1,<2.0.0)
Requires-Dist: urllib3 (>=2.0.4,<3.0.0)
Requires-Dist: validators (>=0.20.0,<0.21.0)
Requires-Dist: webdriver-manager (>=3.8.6,<4.0.0)
Requires-Dist: xlsxwriter (>=3.1.2,<4.0.0)
Requires-Dist: youtube-dl (>=2021.12.17,<2022.0.0)
